koi/__init__.py
koi/__main__.py
koi/constants.py
koi/logger.py
koi/runner.py
koi/utils.py
koi_fish-2.0.1.dist-info/METADATA
koi_fish-2.0.1.dist-info/WHEEL
koi_fish-2.0.1.dist-info/entry_points.txt
koi_fish-2.0.1.dist-info/licenses/LICENSE
koi_fish-2.0.1.dist-info/RECORD
