Metadata-Version: 2.4
Name: koi-fish
Version: 2.0.1
Summary: CLI task runner & automation tool
Keywords: task automation,cli tool,command line runner,task runner
Author-Email: kaliv0 <kaloyan.ivanov88@gmail.com>
License-File: LICENSE
Project-URL: repository, https://github.com/kaliv0/koi_fish.git
Requires-Python: >=3.12
